lakers/__init__.py
lakers/lib2.py
lakers-0.1.dist-info/METADATA
lakers-0.1.dist-info/WHEEL
lakers-0.1.dist-info/top_level.txt
lakers-0.1.dist-info/RECORD
